imggencli/__init__.py
imggencli/cli.py
imggencli-1.4.4.dist-info/License.txt
imggencli-1.4.4.dist-info/METADATA
imggencli-1.4.4.dist-info/WHEEL
imggencli-1.4.4.dist-info/entry_points.txt
imggencli-1.4.4.dist-info/top_level.txt
imggencli-1.4.4.dist-info/RECORD
