Metadata-Version: 2.1
Name: imggencli
Version: 1.4.4
Summary: A command line application to generate customized images based on the Open AI API.
Home-page: https://github.com/shayan-shaikh/Image-generation-CLI
Author: Shayan Shaikh
Author-email: Shaikhshayan1@gmail.com
License: Open Source
Keywords: cli,developer tools,productivity,openai,generative art,ai
Requires-Python: >3.5
License-File: License.txt
Requires-Dist: click (==8.1.3)
Requires-Dist: openai (==0.27.2)
Requires-Dist: rich (==13.3.1)
Requires-Dist: idna
Requires-Dist: pillow
